LICENSE
MANIFEST.in
README.md
setup.cfg
setup.py
django_prosoul.egg-info/PKG-INFO
django_prosoul.egg-info/SOURCES.txt
django_prosoul.egg-info/dependency_links.txt
django_prosoul.egg-info/requires.txt
django_prosoul.egg-info/top_level.txt
prosoul/__init__.py
prosoul/admin.py
prosoul/apps.py
prosoul/data.py
prosoul/data_editor.py
prosoul/forms.py
prosoul/forms_editor.py
prosoul/metrics_import.py
prosoul/models.py
prosoul/prosoul_assess.py
prosoul/prosoul_export.py
prosoul/prosoul_import.py
prosoul/prosoul_metrics.py
prosoul/prosoul_utils.py
prosoul/prosoul_vis.py
prosoul/rest.py
prosoul/tests.py
prosoul/urls.py
prosoul/views.py
prosoul/views_editor.py
prosoul/data/README.md
prosoul/data/alambic_quality_model.json
prosoul/data/basic_maturiy_model.json
prosoul/data/developer_model.json
prosoul/data/developer_model_grimoirelab_eclipse.json
prosoul/data/developer_model_grimoirelab_linuxfoundation2018.json
prosoul/data/developer_model_grimoirelab_mozilla.json
prosoul/data/developer_model_scava.json
prosoul/data/developer_model_scava_scava2es.json
prosoul/data/developer_model_size.json
prosoul/data/developer_model_size_grimoirelab_chaoss.json
prosoul/data/grimoirelab_ossmeter_qm.json
prosoul/data/grimoirelab_qm.json
prosoul/data/iso9126_model.json
prosoul/data/ossmeter_qm.json
prosoul/data/polarsys_qm.json
prosoul/data/qmodel_QualOSS.json
prosoul/migrations/0001_initial.py
prosoul/migrations/0002_auto_20180307_2051.py
prosoul/migrations/0003_metricdata_params.py
prosoul/migrations/0004_auto_20181003_1029.py
prosoul/migrations/__init__.py
prosoul/migrations/__pycache__/0001_initial.cpython-35.pyc
prosoul/migrations/__pycache__/0002_auto_20180307_2051.cpython-35.pyc
prosoul/migrations/__pycache__/0003_metricdata_params.cpython-35.pyc
prosoul/migrations/__pycache__/0004_auto_20181003_1029.cpython-35.pyc
prosoul/migrations/__pycache__/__init__.cpython-35.pyc
prosoul/panels/scava-eclipse-projects-dashboard.json
prosoul/panels/scava-projects-dashboard.json
prosoul/panels/scava-projects-radar.json
prosoul/panels/templates/README.md
prosoul/panels/templates/attribute-template-grimoirelab.json
prosoul/panels/templates/attribute-template.json
