Metadata-Version: 1.2
Name: django-prosoul
Version: 0.4.0
Summary: Prosoul is a software quality models manager to create, import/export, view and edit models
Home-page: https://github.com/bitergia/prosoul
Author: Bitergia
Author-email: acs@bitergia.com
License: GPLv3
Keywords: development repositories analytics quality models assessment visualization
Platform: UNKNOWN
Classifier: Environment :: Web Environment
Classifier: Framework :: Django
Classifier: Framework :: Django :: 2.0
Classifier: Intended Audience :: Customer Service
Classifier: License :: OSI Approved :: GNU General Public License v3 (GPLv3)
Classifier: Operating System :: OS Independent
Classifier: Programming Language :: Python
Classifier: Programming Language :: Python :: 3.5
Classifier: Programming Language :: Python :: 3.6
Classifier: Topic :: Internet :: WWW/HTTP
Classifier: Topic :: Internet :: WWW/HTTP :: Dynamic Content
Requires-Python: >=3.4
